Metadata-Version: 1.2
Name: vergit
Version: 1.0.2
Summary: Tool for getting version info from git history
Home-page: https://github.com/juju-solutions/vergit
Maintainer: Cory Johns
Maintainer-email: johnsca@gmail.com
License: GPL v3
Platform: UNKNOWN
Classifier: Development Status :: 5 - Production/Stable
Classifier: Intended Audience :: Developers
Classifier: Programming Language :: Python
